{
    "last_update": "2026-07-07 13:37:09",
    "stocks": {
        "2330.TW": {
            "name": "台積電",
            "price": 2440.0,
            "pe": 33.17,
            "growth": "35.1%",
            "rsi": 53.51,
            "volume_ratio": 1.03,
            "chips": "☁️ 盤整",
            "support": 2325.1,
            "pressure": 2554.9,
            "atr": 46.07,
            "turnover_zone": 2415.6,
            "buy_point": 2348.08,
            "dynamic_stop": 2324.82,
            "stop_profit_line": 2429.85
        },
        "NVDA": {
            "name": "輝達",
            "price": 192.57,
            "pe": 29.49,
            "growth": "85.2%",
            "rsi": 29.51,
            "volume_ratio": 0.08,
            "chips": "💀 轉弱",
            "support": 183.06,
            "pressure": 202.08,
            "atr": 5.31,
            "turnover_zone": 190.64,
            "buy_point": 184.97,
            "dynamic_stop": 179.29,
            "stop_profit_line": 194.09
        },
        "MU": {
            "name": "美光",
            "price": 925.89,
            "pe": 20.96,
            "growth": "345.7%",
            "rsi": 41.35,
            "volume_ratio": 0.11,
            "chips": "☁️ 盤整",
            "support": 784.1,
            "pressure": 1067.68,
            "atr": 74.98,
            "turnover_zone": 916.63,
            "buy_point": 812.46,
            "dynamic_stop": 738.44,
            "stop_profit_line": 1119.49
        },
        "000660.KS": {
            "name": "海力士",
            "price": 2201000.0,
            "pe": "---",
            "growth": "198.1%",
            "rsi": 43.22,
            "volume_ratio": 1.16,
            "chips": "☁️ 盤整",
            "support": 1808772.79,
            "pressure": 2593227.21,
            "atr": 250571.43,
            "turnover_zone": 2178990.0,
            "buy_point": 1887218.23,
            "dynamic_stop": 1574571.43,
            "stop_profit_line": 2483200.0
        },
        "2303.TW": {
            "name": "聯電",
            "price": 155.0,
            "pe": 39.44,
            "growth": "5.5%",
            "rsi": 58.43,
            "volume_ratio": 0.61,
            "chips": "☁️ 盤整",
            "support": 127.53,
            "pressure": 182.47,
            "atr": 9.71,
            "turnover_zone": 153.45,
            "buy_point": 133.03,
            "dynamic_stop": 130.71,
            "stop_profit_line": 165.38
        },
        "6770.TW": {
            "name": "力積電",
            "price": 70.1,
            "pe": 41.73,
            "growth": "22.1%",
            "rsi": 48.92,
            "volume_ratio": 0.93,
            "chips": "☁️ 盤整",
            "support": 61.32,
            "pressure": 78.88,
            "atr": 5.27,
            "turnover_zone": 69.4,
            "buy_point": 63.07,
            "dynamic_stop": 56.92,
            "stop_profit_line": 72.46
        },
        "2344.TW": {
            "name": "華邦電",
            "price": 174.0,
            "pe": 197.73,
            "growth": "91.3%",
            "rsi": 39.82,
            "volume_ratio": 0.78,
            "chips": "💀 轉弱",
            "support": 141.61,
            "pressure": 206.39,
            "atr": 14.71,
            "turnover_zone": 172.26,
            "buy_point": 148.08,
            "dynamic_stop": 137.21,
            "stop_profit_line": 184.3
        },
        "3481.TW": {
            "name": "群創",
            "price": 64.2,
            "pe": 2140.0,
            "growth": "19.2%",
            "rsi": 64.16,
            "volume_ratio": 1.57,
            "chips": "🔥 強勢",
            "support": 50.78,
            "pressure": 77.62,
            "atr": 5.19,
            "turnover_zone": 63.56,
            "buy_point": 53.47,
            "dynamic_stop": 51.24,
            "stop_profit_line": 67.12
        },
        "1303.TW": {
            "name": "南亞",
            "price": 166.5,
            "pe": 292.11,
            "growth": "4.6%",
            "rsi": 70.04,
            "volume_ratio": 0.96,
            "chips": "🔥 強勢",
            "support": 117.51,
            "pressure": 215.49,
            "atr": 12.5,
            "turnover_zone": 164.84,
            "buy_point": 127.31,
            "dynamic_stop": 135.25,
            "stop_profit_line": 191.09
        }
    }
}