{
    "last_update": "2026-07-21 06:14:04",
    "stocks": {
        "2330.TW": {
            "name": "台積電",
            "price": 2410.0,
            "pe": 32.77,
            "growth": "36.0%",
            "rsi": 41.59,
            "volume_ratio": 0.74,
            "chips": "☁️ 盤整",
            "support": 2329.63,
            "pressure": 2490.37,
            "atr": 47.86,
            "turnover_zone": 2385.9,
            "buy_point": 2345.7,
            "dynamic_stop": 2290.36,
            "stop_profit_line": 2395.9
        },
        "NVDA": {
            "name": "輝達",
            "price": 203.28,
            "pe": 31.04,
            "growth": "85.2%",
            "rsi": 57.45,
            "volume_ratio": 0.69,
            "chips": "☁️ 盤整",
            "support": 194.17,
            "pressure": 212.39,
            "atr": 7.05,
            "turnover_zone": 201.25,
            "buy_point": 195.99,
            "dynamic_stop": 185.65,
            "stop_profit_line": 206.12
        },
        "MU": {
            "name": "美光",
            "price": 865.46,
            "pe": 19.19,
            "growth": "345.7%",
            "rsi": 24.49,
            "volume_ratio": 0.81,
            "chips": "💀 轉弱",
            "support": 696.84,
            "pressure": 1034.08,
            "atr": 60.15,
            "turnover_zone": 856.81,
            "buy_point": 730.56,
            "dynamic_stop": 715.08,
            "stop_profit_line": 953.63
        },
        "000660.KS": {
            "name": "海力士",
            "price": 1842000.0,
            "pe": "---",
            "growth": "198.1%",
            "rsi": 31.07,
            "volume_ratio": 0.55,
            "chips": "💀 轉弱",
            "support": 1331429.0,
            "pressure": 2352571.0,
            "atr": 214571.43,
            "turnover_zone": 1823580.0,
            "buy_point": 1433543.2,
            "dynamic_stop": 1305571.43,
            "stop_profit_line": 2019540.0
        },
        "2303.TW": {
            "name": "聯電",
            "price": 134.5,
            "pe": 34.14,
            "growth": "5.5%",
            "rsi": 34.44,
            "volume_ratio": 1.58,
            "chips": "💀 轉弱",
            "support": 117.05,
            "pressure": 151.95,
            "atr": 9.23,
            "turnover_zone": 133.16,
            "buy_point": 120.54,
            "dynamic_stop": 111.42,
            "stop_profit_line": 161.02
        },
        "6770.TW": {
            "name": "力積電",
            "price": 65.1,
            "pe": 38.75,
            "growth": "22.1%",
            "rsi": 35.35,
            "volume_ratio": 0.5,
            "chips": "💀 轉弱",
            "support": 56.52,
            "pressure": 73.68,
            "atr": 4.1,
            "turnover_zone": 64.45,
            "buy_point": 58.24,
            "dynamic_stop": 54.85,
            "stop_profit_line": 74.2
        },
        "2344.TW": {
            "name": "華邦電",
            "price": 155.5,
            "pe": 176.7,
            "growth": "91.3%",
            "rsi": 31.55,
            "volume_ratio": 0.88,
            "chips": "💀 轉弱",
            "support": 126.67,
            "pressure": 184.33,
            "atr": 11.21,
            "turnover_zone": 153.94,
            "buy_point": 132.44,
            "dynamic_stop": 127.46,
            "stop_profit_line": 175.08
        },
        "3481.TW": {
            "name": "群創",
            "price": 50.7,
            "pe": 1690.0,
            "growth": "19.2%",
            "rsi": 21.11,
            "volume_ratio": 0.92,
            "chips": "💀 轉弱",
            "support": 41.16,
            "pressure": 60.24,
            "atr": 3.76,
            "turnover_zone": 50.19,
            "buy_point": 43.06,
            "dynamic_stop": 41.29,
            "stop_profit_line": 56.74
        },
        "1303.TW": {
            "name": "南亞",
            "price": 195.5,
            "pe": 337.07,
            "growth": "4.6%",
            "rsi": 54.26,
            "volume_ratio": 0.9,
            "chips": "☁️ 盤整",
            "support": 161.64,
            "pressure": 229.36,
            "atr": 15.79,
            "turnover_zone": 193.54,
            "buy_point": 168.41,
            "dynamic_stop": 156.02,
            "stop_profit_line": 220.68
        }
    }
}