{
    "last_update": "2026-07-23 21:15:38",
    "stocks": {
        "2330.TW": {
            "name": "台積電",
            "price": NaN,
            "pe": 32.64,
            "growth": "36.0%",
            "rsi": 45.63,
            "volume_ratio": 0.61,
            "chips": "☁️ 盤整",
            "support": NaN,
            "pressure": NaN,
            "atr": NaN,
            "turnover_zone": NaN,
            "buy_point": NaN,
            "dynamic_stop": NaN,
            "stop_profit_line": NaN
        },
        "NVDA": {
            "name": "輝達",
            "price": 208.76,
            "pe": 31.97,
            "growth": "85.2%",
            "rsi": 62.12,
            "volume_ratio": 0.91,
            "chips": "🔥 強勢",
            "support": 198.98,
            "pressure": 218.54,
            "atr": 7.01,
            "turnover_zone": 206.67,
            "buy_point": 200.93,
            "dynamic_stop": 191.24,
            "stop_profit_line": 205.7
        },
        "MU": {
            "name": "美光",
            "price": 990.21,
            "pe": 22.39,
            "growth": "345.7%",
            "rsi": 51.46,
            "volume_ratio": 0.84,
            "chips": "☁️ 盤整",
            "support": 838.95,
            "pressure": 1141.47,
            "atr": 55.66,
            "turnover_zone": 980.31,
            "buy_point": 869.2,
            "dynamic_stop": 851.06,
            "stop_profit_line": 960.5
        },
        "000660.KS": {
            "name": "海力士",
            "price": 1830000.0,
            "pe": "---",
            "growth": "198.1%",
            "rsi": 32.14,
            "volume_ratio": 0.74,
            "chips": "💀 轉弱",
            "support": 1308254.95,
            "pressure": 2351745.05,
            "atr": 211357.14,
            "turnover_zone": 1811700.0,
            "buy_point": 1412603.96,
            "dynamic_stop": 1301607.14,
            "stop_profit_line": 2019540.0
        },
        "2303.TW": {
            "name": "聯電",
            "price": NaN,
            "pe": 35.24,
            "growth": "5.5%",
            "rsi": 35.37,
            "volume_ratio": 0.54,
            "chips": "💀 轉弱",
            "support": NaN,
            "pressure": NaN,
            "atr": NaN,
            "turnover_zone": NaN,
            "buy_point": NaN,
            "dynamic_stop": NaN,
            "stop_profit_line": NaN
        },
        "6770.TW": {
            "name": "力積電",
            "price": NaN,
            "pe": 39.29,
            "growth": "22.1%",
            "rsi": 41.54,
            "volume_ratio": 0.49,
            "chips": "☁️ 盤整",
            "support": NaN,
            "pressure": NaN,
            "atr": NaN,
            "turnover_zone": NaN,
            "buy_point": NaN,
            "dynamic_stop": NaN,
            "stop_profit_line": NaN
        },
        "2344.TW": {
            "name": "華邦電",
            "price": NaN,
            "pe": 47.77,
            "growth": "91.3%",
            "rsi": 43.35,
            "volume_ratio": 1.4,
            "chips": "☁️ 盤整",
            "support": NaN,
            "pressure": NaN,
            "atr": NaN,
            "turnover_zone": NaN,
            "buy_point": NaN,
            "dynamic_stop": NaN,
            "stop_profit_line": NaN
        },
        "3481.TW": {
            "name": "群創",
            "price": NaN,
            "pe": 1730.0,
            "growth": "19.2%",
            "rsi": 26.64,
            "volume_ratio": 0.75,
            "chips": "💀 轉弱",
            "support": NaN,
            "pressure": NaN,
            "atr": NaN,
            "turnover_zone": NaN,
            "buy_point": NaN,
            "dynamic_stop": NaN,
            "stop_profit_line": NaN
        },
        "1303.TW": {
            "name": "南亞",
            "price": NaN,
            "pe": 351.79,
            "growth": "4.6%",
            "rsi": 53.84,
            "volume_ratio": 1.01,
            "chips": "☁️ 盤整",
            "support": NaN,
            "pressure": NaN,
            "atr": NaN,
            "turnover_zone": NaN,
            "buy_point": NaN,
            "dynamic_stop": NaN,
            "stop_profit_line": NaN
        }
    }
}